[
  {
    "uuid": "55bc2cc6-bd5c-52bc-9354-a134ee826ce4",
    "entry": "悩乱",
    "reading": {
      "primary": "のうらん",
      "alternatives": [],
      "is_heteronym": false
    },
    "grammar": {
      "pos": [
        "名詞",
        "動詞-サ変",
        "動詞-自動詞"
      ],
      "ctype": null,
      "inflections": null
    },
    "definitions": [
      {
        "index": 1,
        "gloss": "worry",
        "register": "standard",
        "nuance": null,
        "scenarios": [],
        "sensory_tags": {
          "colors": [],
          "temperature": null,
          "sounds": [],
          "emotions": []
        },
        "collocations": [],
        "examples": {
          "standard": [],
          "literary": [
            {
              "text": "若不順我呪　悩乱説法者頭破作七分　如阿梨樹枝如殺父母罪　亦如厭油殃斗秤欺誑人　調達破僧罪犯此法師者　当獲如是殃　と一心不乱、さっと木の葉を捲いて風が南へ吹いたが、たちまち静り返った、夫婦が閨もひッそりした。",
              "citation": {
                "source": "高野聖",
                "author": "泉鏡花",
                "note": "青空文庫"
              }
            },
            {
              "text": "」と振向き状に、ぶつきら棒に立つて、握拳で、額を擦つたのが、悩乱した頭の髪を、掻※りでもしたさうに見えて、煙の靡く天井を仰いだ。",
              "citation": {
                "source": "続銀鼎",
                "author": "泉鏡太郎",
                "note": "青空文庫"
              }
            },
            {
              "text": "また、うっかり注射でも怠ろうものなら、恐水病といって、発熱悩乱の苦しみあって、果ては貌が犬に似てきて、四つ這いになり、ただわんわんと吠ゆるばかりだという、そんな凄惨な病気になるかもしれないということなのである。",
              "citation": {
                "source": "畜犬談",
                "author": "―伊馬鵜平君に与える―",
                "note": "青空文庫"
              }
            },
            {
              "text": "意気張ずくで死んで見せように到っては、益々悩乱のほどが思い遣られる。",
              "citation": {
                "source": "春昼後刻",
                "author": "泉鏡花",
                "note": "青空文庫"
              }
            },
            {
              "text": "はっと思うに毒や利きけむ、心身たちまち悩乱して、腸絞る苦しさにさては毒をば飲まされたり。",
              "citation": {
                "source": "活人形",
                "author": "泉鏡花",
                "note": "青空文庫"
              }
            },
            {
              "text": "ああ、恋しい人のふみを抱いて、私は心も悩乱した、姥、許して！",
              "citation": {
                "source": "夜叉ヶ池",
                "author": "泉鏡花",
                "note": "青空文庫"
              }
            },
            {
              "text": "ちやうど、こどもが銭亀を見つけたやうに、水に泳がしたり、桶の椽に匍はしたり、仰向けにしてみたり、自分と同じ大きさの人間でないのが気になるのだ」　小布施は欧洲の桂子から精力的に書き寄越した新興画派の紹介なり、自説の感想なり、意見なりに、どの位悩乱され衝動されたか知れないのであつた。",
              "citation": {
                "source": "花は勁し",
                "author": "岡本かの子",
                "note": "青空文庫"
              }
            },
            {
              "text": "殿に金鉄の我が心も、波打つばかり悩乱をいたします。",
              "citation": {
                "source": "天守物語",
                "author": "泉鏡花",
                "note": "青空文庫"
              }
            },
            {
              "text": "……　それから悩乱。",
              "citation": {
                "source": "菎蒻本",
                "author": "泉鏡花",
                "note": "青空文庫"
              }
            },
            {
              "text": "若不順我咒　　悩乱説法者　　頭破作七分如阿梨樹枝　　如殺父母罪　　亦如厭油殃斗秤欺誰人　　調達僧罪犯　　犯此法師者当獲如是殃と一｜心不乱。",
              "citation": {
                "source": "高野聖",
                "author": "泉鏡太郎",
                "note": "青空文庫"
              }
            },
            {
              "text": "若い、優しい女が裸体、いや、裸体じゃないが、縁の柱に縛られた、それまでのかよわい抵抗、悩乱が思われる。",
              "citation": {
                "source": "雪柳",
                "author": "泉鏡花",
                "note": "青空文庫"
              }
            },
            {
              "text": "その上に大酔悩乱です。",
              "citation": {
                "source": "雪柳",
                "author": "泉鏡花",
                "note": "青空文庫"
              }
            },
            {
              "text": "宮が心地｜勝れずなりてより、彼に対する貫一の優しさはその平生に一層を加へたれば、彼は死を覓むれども得ず、生を求むれども得ざらんやうに、悩乱してほとほとその堪ふべからざる限に至りぬ。",
              "citation": {
                "source": "金色夜叉",
                "author": "尾崎紅葉",
                "note": "青空文庫"
              }
            },
            {
              "text": "これを表沙汰にせば債務者は論無う刑法の罪人たらざるべからず、ここに於て誰か恐慌し、狼狽し、悩乱し、号泣し、死力を竭して七所借の調達を計らざらん。",
              "citation": {
                "source": "金色夜叉",
                "author": "尾崎紅葉",
                "note": "青空文庫"
              }
            },
            {
              "text": "貫一は活を求めて得ず、死を覓めて得ず、居れば立つを念ひ、立てば臥すを想ひ、臥せば行くを懐ひ、寐ぬれば覚め、覚むれば思ひて、夜もあらず、日もあらず、人もあらず、世もあらで、唯憂ひ惑へる己一個の措所無く可煩きに悩乱せり。",
              "citation": {
                "source": "金色夜叉",
                "author": "尾崎紅葉",
                "note": "青空文庫"
              }
            },
            {
              "text": "『正法念処経』にいわく、瞋痴多行の者、大海中に生まれて毒竜となり、共に瞋悩乱心毒を吐いて相害し、常に悪業を行う。",
              "citation": {
                "source": "十二支考",
                "author": "田原藤太竜宮入りの話",
                "note": "青空文庫"
              }
            },
            {
              "text": "与五郎と玉琴は毒酒にあたりし体にて、身神俄かに悩乱す。",
              "citation": {
                "source": "平家蟹",
                "author": "岡本綺堂",
                "note": "青空文庫"
              }
            },
            {
              "text": "与五郎　今かの酒を飲むとひとしく、俄かに身神悩乱して……ふたりが二人ながら苦痛に堪えぬは……。",
              "citation": {
                "source": "平家蟹",
                "author": "岡本綺堂",
                "note": "青空文庫"
              }
            },
            {
              "text": "前者は自己の不幸に遭遇すると、しばしば烈しい悩乱となり、後者は自己の不幸に遭遇すると、しばしば孤立的な枯渇を来すものらしい。",
              "citation": {
                "source": "ラ氏の笛",
                "author": "松永延造",
                "note": "青空文庫"
              }
            },
            {
              "text": "ヴェデキントは作家としての特質から、少年少女の性の目覚めの悩乱を、今日の感覚からみると極端まで中核におきすぎて、その点で登場する若い人物たちは動物的に性的な一面へ歪められすぎた暗い姿を現している。",
              "citation": {
                "source": "若き精神の成長を描く文学",
                "author": "宮本百合子",
                "note": "青空文庫"
              }
            },
            {
              "text": "すべてしろいもののなかにかくれふしてゆく僧形のばらの花、ただれる憂欝、くされ　とけてながれる悩乱の花束、美貌の情欲、くろぐろとけむる叡智の犬、わたしの両手はくさりにつながれ、ほそいうめきをたててゐる。",
              "citation": {
                "source": "藍色の蟇",
                "author": "大手拓次",
                "note": "青空文庫"
              }
            },
            {
              "text": "わけても妾の兄｜御前二人は、此程引続きて悩乱の態となり、長兄は介隈の墓所を発き、次兄は妾を石にて打たむと仕るなぞ、恐ろしき事のみ致したる果、相次ぎて生命を早め侍りしばかりにて、さる噂、一際高まりたる折節に候へば大抵の家の者は暇を請ひ去り、永年召し使ひたる者も、妾を見候てため息を仕るのみ。",
              "citation": {
                "source": "ドグラ・マグラ",
                "author": "夢野久作",
                "note": "青空文庫"
              }
            },
            {
              "text": "もしそれを取って胃袋の中へでも送ろうものならば、たちどころに内臓の全部を顛覆し、人間の外体を一昼夜もころげ廻って悩乱させ、その全身を紫斑色にして虐殺してしまう。",
              "citation": {
                "source": "大菩薩峠",
                "author": "畜生谷の巻",
                "note": "青空文庫"
              }
            },
            {
              "text": "「汝のために、武蔵屋で、紙帳の中へ引き入れられ、気絶させられ、悩乱させられたばかりに、頼母様に差し上げようと思った天国様を川へおとし、そればかりか、五郎蔵に捕えられ、『俺を裏切り、頼母へ心中立てした憎い女！",
              "citation": {
                "source": "血曼陀羅紙帳武士",
                "author": "国枝史郎",
                "note": "青空文庫"
              }
            },
            {
              "text": "）　悪党の彼ではあったけれど、このことを思えば身が震えるのであったが、悩乱状態の陣十郎には、やはりこの事も冷静な気持で、回想することなど出来なかった。",
              "citation": {
                "source": "剣侠",
                "author": "国枝史郎",
                "note": "青空文庫"
              }
            },
            {
              "text": "」悩乱した頭脳にも感じられたのは、処女性を備えた豊満の肉体。",
              "citation": {
                "source": "任侠二刀流",
                "author": "国枝史郎",
                "note": "青空文庫"
              }
            },
            {
              "text": "不馴れのためにペンが横へ外れるかも知れませんが、頭が悩乱して筆がしどろに走るのではないように思います。",
              "citation": {
                "source": "こころ",
                "author": "夏目漱石",
                "note": "青空文庫"
              }
            },
            {
              "text": "この場をどう切り抜けたらいいか知らという思慮の悩乱でもあった。",
              "citation": {
                "source": "明暗",
                "author": "夏目漱石",
                "note": "青空文庫"
              }
            },
            {
              "text": "悩乱のうちにまだ一分の商量を余した利巧な彼女は、夫のかけた鎌を外さずに、すぐ向うへかけ返した。",
              "citation": {
                "source": "明暗",
                "author": "夏目漱石",
                "note": "青空文庫"
              }
            },
            {
              "text": "二つのものを結びつけて矛盾なく考えようとする時、悩乱は始めて起るので、離して眺めれば、甲が事実であったごとく、乙もやッぱり本当でなければならなかった。",
              "citation": {
                "source": "明暗",
                "author": "夏目漱石",
                "note": "青空文庫"
              }
            }
          ]
        }
      }
    ],
    "relations": {
      "homophones": [],
      "synonyms": [],
      "antonyms": [],
      "related": []
    },
    "meta": {
      "version": "1.0.0",
      "source": "JMdict, Aozora-Crawler, Illusions-Core",
      "updated_at": "2026-03-22T12:50:57Z"
    }
  }
]