[
  {
    "uuid": "d107037e-413b-5727-864b-3df99bddca87",
    "entry": "民",
    "reading": {
      "primary": "たみ",
      "alternatives": [],
      "is_heteronym": false
    },
    "grammar": {
      "pos": [
        "名詞"
      ],
      "ctype": null,
      "inflections": null
    },
    "definitions": [
      {
        "index": 1,
        "gloss": "people",
        "register": "standard",
        "nuance": null,
        "scenarios": [],
        "sensory_tags": {
          "colors": [],
          "temperature": null,
          "sounds": [],
          "emotions": []
        },
        "collocations": [],
        "examples": {
          "standard": [],
          "literary": [
            {
              "text": "のみならず、此処には、我が民謡の精神は実になみ／＼としてゐて、これは、詩書を手にする程の人には最も直ちに、感じられる底のものである。",
              "citation": {
                "source": "宮沢賢治全集",
                "author": "中原中也",
                "note": "青空文庫"
              }
            },
            {
              "text": "此の我々の感性に近いもの、寧ろ民謡でさへある殉情詩が、此の殉情的な国で、今迄読まれなかつたなぞといふことは不思議だと、今度此の全集の第一巻が出た後では、諸君も必ずやさうお思ひになることと思ひます。",
              "citation": {
                "source": "宮沢賢治全集刊行に際して",
                "author": "中原中也",
                "note": "青空文庫"
              }
            },
            {
              "text": "さういふと、外国人はたゞもう楽天的で、我々は唯もう渋い一天張りの国民のやうな気もするが、そんなことは、一朝にして決められることではない。",
              "citation": {
                "source": "海の詩",
                "author": "――人と海――",
                "note": "青空文庫"
              }
            },
            {
              "text": "扨、新短歌が今後益々作られることに、異存のあるわけもないが、新短歌が「生活の余暇的なもの」といふ私の考へにして間違ひがないならば、新短歌が民族詩歌の発展に寄与する所は少ないであらう。",
              "citation": {
                "source": "新短歌に就いて",
                "author": "中原中也",
                "note": "青空文庫"
              }
            },
            {
              "text": "植民地一揆が起つてゐたのだ。",
              "citation": {
                "source": "デボルド―※ルモオル",
                "author": "中原中也",
                "note": "青空文庫"
              }
            },
            {
              "text": "此の十九世期の一仏蘭西女、此のフェイドオ劇場の一女優、此の巡業家の妻、此の子供を育てるに実に良心的でやさしさ此の上もなかつた一小市民――それがコリンヌ風な意味ででもサッフォ風な意味ででも抒情的な詩人であつたといふわけである。",
              "citation": {
                "source": "デボルド―※ルモオル",
                "author": "中原中也",
                "note": "青空文庫"
              }
            },
            {
              "text": "政府が盆踊を禁ずるのも、国民が欧米人の真似をするのも、固有の日本文化が亡びるのも、すべて皆基督教の宣教師が宣伝するためであり、一切の悪は耶蘇教の罪に帰せられた。",
              "citation": {
                "source": "小泉八雲の家庭生活",
                "author": "室生犀星と佐藤春夫の二詩友を偲びつつ",
                "note": "青空文庫"
              }
            },
            {
              "text": "なぜなら鳥や虫の生活の方が、人間よりも不幸であるとは思えないから』と、あるエッセイの中で書いてるヘルンは、日本人の民族化した仏教情操であるところの、あの『物のあわれ』の抒情的ペーソスを知ってたのである。",
              "citation": {
                "source": "小泉八雲の家庭生活",
                "author": "室生犀星と佐藤春夫の二詩友を偲びつつ",
                "note": "青空文庫"
              }
            },
            {
              "text": "ヘルンの趣味はすべてにおいて庶民的で、儀式ばったことが嫌いなので、フロックコートなどの礼服を非常に嫌い、常に野蛮人の服と称し『なんぼ野蛮の物』と言っていた。",
              "citation": {
                "source": "小泉八雲の家庭生活",
                "author": "室生犀星と佐藤春夫の二詩友を偲びつつ",
                "note": "青空文庫"
              }
            },
            {
              "text": "あなたの大好きな魯迅先生は、所謂「革命」に依る民衆の幸福の可能性を懐疑し、まず民衆の啓蒙に着眼しました。",
              "citation": {
                "source": "返事",
                "author": "太宰治",
                "note": "青空文庫"
              }
            },
            {
              "text": "私は新聞に発表せられている事をそのとおりに信じ、それ以上の事は知ろうとも思わない極めて平凡な国民なのである。",
              "citation": {
                "source": "佳日",
                "author": "太宰治",
                "note": "青空文庫"
              }
            },
            {
              "text": "偶然にも貧民階級の上にだけ生活があつた！",
              "citation": {
                "source": "生と歌",
                "author": "中原中也",
                "note": "青空文庫"
              }
            },
            {
              "text": "――因みに、各民族の古い時代には、俳句の如く短詩形があり、それがまた非常に微妙なものであつたといふことを、俳句がそれに相当するといふのではないまでも、一応想起されたいのである。",
              "citation": {
                "source": "詩と其の伝統",
                "author": "中原中也",
                "note": "青空文庫"
              }
            },
            {
              "text": "その上での作品でない限り、アマチュア芸だし、民族の詩となる日は来ないのである。",
              "citation": {
                "source": "詩と其の伝統",
                "author": "中原中也",
                "note": "青空文庫"
              }
            },
            {
              "text": "人に対して平静、順応的にしてアクティヴに非ざる限り、我等が民族の文学は何時迄も反復に終るであらう。",
              "citation": {
                "source": "詩に関する話",
                "author": "中原中也",
                "note": "青空文庫"
              }
            },
            {
              "text": "みんな下層民の寄り集りぢやあないか。",
              "citation": {
                "source": "その頃の生活",
                "author": "中原中也",
                "note": "青空文庫"
              }
            },
            {
              "text": "流行歌曲について萩原朔太郎　現代の日本に於ける、唯一の民衆芸術は何かと聞かれたら、僕は即座に町の小唄と答へるだらう。",
              "citation": {
                "source": "流行歌曲について",
                "author": "萩原朔太郎",
                "note": "青空文庫"
              }
            },
            {
              "text": "文壇の文学である詩や小説は、民衆の現実生活から遊離して、単なるインテリのデレツタンチズムになつて居るし、政府の官営してゐる学校音楽といふものも、同じやうに民衆の生活感情と縁がないのだ。",
              "citation": {
                "source": "流行歌曲について",
                "author": "萩原朔太郎",
                "note": "青空文庫"
              }
            },
            {
              "text": "真に今日、日本の現実する社会相と接触し、民衆のリアルな喜怒哀楽を表現してゐる芸術は、蓄音機のレコード等によつて唄はれてる、町の流行唄以外にないのである。",
              "citation": {
                "source": "流行歌曲について",
                "author": "萩原朔太郎",
                "note": "青空文庫"
              }
            },
            {
              "text": "この股旅小唄の主旋律は、概して皆尺八的、浪花節的哀傷を帯びてるもので、日本人の民族的リリシズムとも言ふべき、旅への放浪情操をよく表現して居た。",
              "citation": {
                "source": "流行歌曲について",
                "author": "萩原朔太郎",
                "note": "青空文庫"
              }
            },
            {
              "text": "たまたまさうでなかつたものは、儒教等の影響がすくないところの、別の時代や庶民階級から生れたのである。",
              "citation": {
                "source": "童話と教育について",
                "author": "萩原朔太郎",
                "note": "青空文庫"
              }
            },
            {
              "text": "耳で聽いて意味がわからず、文字に書いて見せた上で、初めて視覺から語意が通ずるといふやうな言葉を、日常語の會話に使用するやうな國民があるとしたら、世界で最も不便で最惡の國語を所有する民族と言はねばならぬ。",
              "citation": {
                "source": "ローマ字論者への質疑",
                "author": "萩原朔太郎",
                "note": "青空文庫"
              }
            },
            {
              "text": "支那文字の輸入以來、我々は漢語のデタラメな無韻的和讀によつて、著るしく「耳の健康」を障害し、言語上の音痴民族となつてしまつた。",
              "citation": {
                "source": "ローマ字論者への質疑",
                "author": "萩原朔太郎",
                "note": "青空文庫"
              }
            },
            {
              "text": "元来日本文化は、上古の奈良朝時代までは、海外雄飛の建国時代であったため、人心が自由で明るく、浪漫的の青春性に富んでいたのであるが、その後次第に鎖国的となり、人民の自由が束縛されたため、文学の情操も隠遁的、老境的となり、上古万葉の歌に見るような青春性をなくしてしまった。",
              "citation": {
                "source": "郷愁の詩人　与謝蕪村",
                "author": "萩原朔太郎",
                "note": "青空文庫"
              }
            },
            {
              "text": "然るに日本人は、歴史的に思想を持たない国民であるから、本来哲学的の思想を根とする西洋文学の輸入に際して一もそれに適応する原語がなく、日本語字典のあらゆる言海を探した後で、止むを得ず「現実」や「自然」などといふ訳語を、無理にこじつけて適当させた。",
              "citation": {
                "source": "詩の翻訳について",
                "author": "萩原朔太郎",
                "note": "青空文庫"
              }
            },
            {
              "text": "外国文化の輸入に於て、翻訳が絶対に不可能のこと、実には「翻案」しか有り得ないこと、そして結局、すべての外国文化の輸入は、国民自身の主観的な「創作」に過ぎないことは、以上の一例によつても解るのである。",
              "citation": {
                "source": "詩の翻訳について",
                "author": "萩原朔太郎",
                "note": "青空文庫"
              }
            },
            {
              "text": "それから、また志士や学者が言っているような「民衆」というような人間は捜してみると存外容易に見つからない。",
              "citation": {
                "source": "春六題",
                "author": "寺田寅彦",
                "note": "青空文庫"
              }
            },
            {
              "text": "みよ兄は手に水桃をささげもち、いつさんにきみがかたへにしたひよる、この東京の日くれどき、兄の戀魚は青らみてゆきて、日毎にいたみしたたり、いまいきもたえだえ、あい子よ、ふたり哀しき日のしたに、ひとしれず草木の種を研ぐとても、さびしきはげに我等の素脚ならずや。",
              "citation": {
                "source": "幼き妹に",
                "author": "萩原朔太郎",
                "note": "青空文庫"
              }
            },
            {
              "text": "感傷の塔萩原朔太郎塔は額にきづかる、螢をもつて窓をあかるくし、塔はするどく青らみ空に立つ、ああ我が塔をきづくの額は血みどろ、肉やぶれいたみふんすゐすれども、なやましき感傷の塔は光に向ひて伸長す、いやさらに伸長し、その愁も青空にとがりたり。",
              "citation": {
                "source": "感傷の塔",
                "author": "萩原朔太郎",
                "note": "青空文庫"
              }
            },
            {
              "text": "宗谷〔一〕宮沢賢治まくろなる流れの岸に根株燃すゆふべのけむりこらつどひかたみに舞ひてたんぽゝの白き毛をふく丘の上のスリッパ小屋に媼ゐてむすめらに云ふかくてしも畑みな成りてあらたなる艱苦ひらくと",
              "citation": {
                "source": "宗谷〔一〕",
                "author": "宮沢賢治",
                "note": "青空文庫"
              }
            }
          ]
        }
      }
    ],
    "relations": {
      "homophones": [],
      "synonyms": [],
      "antonyms": [],
      "related": []
    },
    "meta": {
      "version": "1.0.0",
      "source": "JMdict, Aozora-Crawler, Illusions-Core",
      "updated_at": "2026-03-22T12:50:57Z",
      "freq_rank": 3052
    }
  }
]