[
  {
    "uuid": "ddd140ed-b5eb-5c36-b1f1-ed1268276572",
    "entry": "人生記録",
    "reading": {
      "primary": "じんせいきろく",
      "alternatives": [],
      "is_heteronym": false
    },
    "grammar": {
      "pos": [
        "名詞"
      ],
      "ctype": null,
      "inflections": null
    },
    "definitions": [
      {
        "index": 1,
        "gloss": "human document",
        "register": "standard",
        "nuance": null,
        "scenarios": [],
        "sensory_tags": {
          "colors": [],
          "temperature": null,
          "sounds": [],
          "emotions": []
        },
        "collocations": [],
        "examples": {
          "standard": [],
          "literary": [
            {
              "text": "歴史を下から見たものの人生記録でもない。",
              "citation": {
                "source": "今日の文学の展望",
                "author": "宮本百合子",
                "note": "青空文庫"
              }
            },
            {
              "text": "この作、もと二部より成るが、本来なら更に一部を書き足し全体を三部作ともして、結局この作の主人公が遠い旅から抱いて来た心に帰って行くまでを書いて見なければ、全局の見通しもつきかねるような作で、人生記録としてもまことに不充分なものではある。",
              "citation": {
                "source": "新生",
                "author": "島崎藤村",
                "note": "青空文庫"
              }
            },
            {
              "text": "新聞の三面記事にも等しい人生記録という奴がその一つである。",
              "citation": {
                "source": "ヒューメーンということに就て",
                "author": "豊島与志雄",
                "note": "青空文庫"
              }
            },
            {
              "text": "自然主義から脱け出そうとした作家の多くが私小説を書いたことは、事実であるが、自然主義の所謂人生記録の尊重は、各作家の理念傾向を超えて、私小説を暗々裡に支援した。",
              "citation": {
                "source": "文学に於ける構想力",
                "author": "豊島与志雄",
                "note": "青空文庫"
              }
            },
            {
              "text": "低級な私小説はともかく、高級な私小説に於ては、嘗て人生記録が尊重されたように、少しく改名して、人間記録が尊重されるかも知れない。",
              "citation": {
                "source": "文学に於ける構想力",
                "author": "豊島与志雄",
                "note": "青空文庫"
              }
            },
            {
              "text": "人生記録は既に遠くの彼方に眺められる。",
              "citation": {
                "source": "文学に於ける構想力",
                "author": "豊島与志雄",
                "note": "青空文庫"
              }
            },
            {
              "text": "藤村君の人生記録はかゝる魂の仕事場から鍛へ出されたのである。",
              "citation": {
                "source": "緑蔭叢書創刊期",
                "author": "蒲原有明",
                "note": "青空文庫"
              }
            },
            {
              "text": "この初めて舞台にのせられた厳粛な「人生記録」の中に、当時の演劇批評家は、真に戯曲的なものを発見することができず、ベックはために作家として不遇な生涯を終らなければならなかつた。",
              "citation": {
                "source": "近代劇論",
                "author": "岸田國士",
                "note": "青空文庫"
              }
            },
            {
              "text": "しかし通常、記録の表面にあらはれた事件の部分は常套的な人生記録で、よし三面記事的乃至は大衆小説的な興味を寄せ得ても、人生を知る材料には割合に乏しいものである。",
              "citation": {
                "source": "戦争と文化",
                "author": "――力としての文化　第三話",
                "note": "青空文庫"
              }
            },
            {
              "text": "それはすべて、我が人生記録である。",
              "citation": {
                "source": "利根川の鮎",
                "author": "佐藤垢石",
                "note": "青空文庫"
              }
            },
            {
              "text": "ひと組の夫婦といふものが、戀愛か、見合か、盛大な結婚式をされて門出したか、また巷の裏で、貧しい誓ひをやつた仲か、とにかく、出發はどうでも、お互が、かうなる迄、一つに暮して來たといふことは、たいへんな人生記録の保持者です。",
              "citation": {
                "source": "折々の記",
                "author": "吉川英治",
                "note": "青空文庫"
              }
            },
            {
              "text": "そして録音技師は陰雨の中に悶死を遂げ、実に、令嬢の日記こそ、人間生活の真実を描けるもの、かえって推称し得べき正直無比なる人生記録であったが、問題はたださえ世の中が同情と痛惜に沸き立っている真っ最中にこういう人間の真実性を伝えていいかどうかであった。",
              "citation": {
                "source": "令嬢エミーラの日記",
                "author": "橘外男",
                "note": "青空文庫"
              }
            },
            {
              "text": "けれど、人となりの違い、性格の違い、やや急転して来る時代の違いなどから、その短い人生記録は、義仲とはまた、まったく違う義経でもある。",
              "citation": {
                "source": "随筆　新平家",
                "author": "吉川英治",
                "note": "青空文庫"
              }
            }
          ]
        }
      }
    ],
    "relations": {
      "homophones": [],
      "synonyms": [],
      "antonyms": [],
      "related": []
    },
    "meta": {
      "version": "1.0.0",
      "source": "JMdict, Aozora-Crawler, Illusions-Core",
      "updated_at": "2026-03-22T12:50:57Z"
    }
  }
]