[
  {
    "uuid": "5ad99d5f-6669-5f6a-a591-d0c5e7237d18",
    "entry": "重傷者",
    "reading": {
      "primary": "じゅうしょうしゃ",
      "alternatives": [],
      "is_heteronym": false
    },
    "grammar": {
      "pos": [
        "名詞"
      ],
      "ctype": null,
      "inflections": null
    },
    "definitions": [
      {
        "index": 1,
        "gloss": "severely wounded person",
        "register": "standard",
        "nuance": null,
        "scenarios": [],
        "sensory_tags": {
          "colors": [],
          "temperature": null,
          "sounds": [],
          "emotions": []
        },
        "collocations": [],
        "examples": {
          "standard": [],
          "literary": [
            {
              "text": "それ故、役員は、死者を重傷者にして病院へかつぎこませる。",
              "citation": {
                "source": "土鼠と落盤",
                "author": "黒島傳治",
                "note": "青空文庫"
              }
            },
            {
              "text": "見ると或地方で小学校新築落成式を挙げし当日、廊の欄が倒れて四五十人の児童庭に顛落し重傷者二名、軽傷者三十名との珍事の報道である。",
              "citation": {
                "source": "酒中日記",
                "author": "国木田独歩",
                "note": "青空文庫"
              }
            },
            {
              "text": "それを、飲ますことが、こうした重傷者に何う云う結果を及ぼすかは、ハッキリと判らなかった。",
              "citation": {
                "source": "真珠夫人",
                "author": "菊池寛",
                "note": "青空文庫"
              }
            },
            {
              "text": "が、此場合瀕死の重傷者に、鍵の在処を尋ねるなどは、余りに心ないことだった。",
              "citation": {
                "source": "真珠夫人",
                "author": "菊池寛",
                "note": "青空文庫"
              }
            },
            {
              "text": "そして死に切れない重傷者のうめきが、思い出したように時々きこえてきた。",
              "citation": {
                "source": "ゼラール中尉",
                "author": "菊池寛",
                "note": "青空文庫"
              }
            },
            {
              "text": "あの僕の眼に灼きつけられてゐる赤く爛れたむくむくの死体と黒焦の重傷者の蠢く世界が、何だか原始時代の悪夢のやうにおもへた。",
              "citation": {
                "source": "長崎の鐘",
                "author": "原民喜",
                "note": "青空文庫"
              }
            },
            {
              "text": "ただ一つだけ、明確にわかつてゐることがらは、あの広島の惨劇のなかに横はる塁々たる重傷者の、そのか弱い声の、それらの声が、等しく天にむかつて訴へてゐることが何であるかといふことだ。",
              "citation": {
                "source": "戦争について",
                "author": "原民喜",
                "note": "青空文庫"
              }
            },
            {
              "text": "よくみると、それは無惨にも片足を失った重傷者が、救いを求めているのであった。",
              "citation": {
                "source": "仲々死なぬ彼奴",
                "author": "海野十三",
                "note": "青空文庫"
              }
            },
            {
              "text": "というのは、その片足のない重傷者は、その日、葬儀をした筈の大熊老人その人に違いなかったから……　後で判明したことは、大熊老人は毒殺されたが、平常の抗毒方法がうまく効いて、棺の中に居るうち段々恢復してきた。",
              "citation": {
                "source": "仲々死なぬ彼奴",
                "author": "海野十三",
                "note": "青空文庫"
              }
            },
            {
              "text": "重傷者ができましたから、この車を鳥渡拝借したい」と中国人は丁寧に、だが圧しつけるような口の利き方をした。",
              "citation": {
                "source": "人造人間殺害事件",
                "author": "海野十三",
                "note": "青空文庫"
              }
            },
            {
              "text": "恐しい記憶や惨めな重傷者の姿は、まだ日毎目の前にあった。",
              "citation": {
                "source": "遥かな旅",
                "author": "原民喜",
                "note": "青空文庫"
              }
            },
            {
              "text": "他に照空灯、聴音機等若干の損害を受けましたが、爾後の戦闘には、支障なき程度でございます」「軍隊以外の死傷は」「死者約七十名、重傷者約二百名、生死不明者約千名であります。",
              "citation": {
                "source": "空襲警報",
                "author": "海野十三",
                "note": "青空文庫"
              }
            },
            {
              "text": "が、此場合瀕死の重傷者に、鍵の在処を尋ねるなどは、余りに心ないことだつた。",
              "citation": {
                "source": "真珠夫人",
                "author": "菊池寛",
                "note": "青空文庫"
              }
            },
            {
              "text": "待合紅高砂の玄関を出た途端に、あの不意打ちの狙撃事件が起り、重傷者を出すやら、病院まで付き添ってゆくやらで自分一人になる自由を持たなかった。",
              "citation": {
                "source": "深夜の市長",
                "author": "海野十三",
                "note": "青空文庫"
              }
            },
            {
              "text": "イラン勢も、ほぼ同数の者を失ったが、重傷者は、却ってツラン方より多いという噂が伝わった。",
              "citation": {
                "source": "古き小画",
                "author": "宮本百合子",
                "note": "青空文庫"
              }
            },
            {
              "text": "だが、その上にはやはり瀕死の重傷者が臥してゐて、既にどうにもならないのであつた。",
              "citation": {
                "source": "夏の花",
                "author": "原民喜",
                "note": "青空文庫"
              }
            },
            {
              "text": "境内到る処に重傷者はごろごろしてゐたが、テントも木蔭も見あたらない。",
              "citation": {
                "source": "夏の花",
                "author": "原民喜",
                "note": "青空文庫"
              }
            },
            {
              "text": "擦れ違ふ列車はみな奇怪な重傷者を満載してゐた。",
              "citation": {
                "source": "夏の花",
                "author": "原民喜",
                "note": "青空文庫"
              }
            },
            {
              "text": "Ｎはいたるところの収容所を訪ね廻つて、重傷者の顔を覗き込んだ。",
              "citation": {
                "source": "夏の花",
                "author": "原民喜",
                "note": "青空文庫"
              }
            },
            {
              "text": "……火焔のなかを突切って、河原まで逃げて来ると、そこには異形の裸体の重傷者がずらりと並んでいる。",
              "citation": {
                "source": "火の唇",
                "author": "原民喜",
                "note": "青空文庫"
              }
            },
            {
              "text": "板の間の筵の上にごろごろしている重傷者のなかに黒く腫れ上った少女の顔がある。",
              "citation": {
                "source": "火の唇",
                "author": "原民喜",
                "note": "青空文庫"
              }
            },
            {
              "text": "庭を隔てて母屋の方の縁側に、ひどく顔の腫れ上った男の姿――そんな風な顔はもう見倦る程見せられた――が伺われたし、奥の方にはもっと重傷者がいるらしく、床がのべてあった。",
              "citation": {
                "source": "廃墟から",
                "author": "原民喜",
                "note": "青空文庫"
              }
            },
            {
              "text": "――手押車で運ばれて来る、老人の重傷者、顔と手を火傷している中学生、――彼は東練兵場で遭難したのだそうだ。",
              "citation": {
                "source": "廃墟から",
                "author": "原民喜",
                "note": "青空文庫"
              }
            },
            {
              "text": "もし彼女が途中で遭難しているとすれば、あの沢山の重傷者の顔と同じように、想っても、ぞっとするような姿に変り果てたことだろう。",
              "citation": {
                "source": "廃墟から",
                "author": "原民喜",
                "note": "青空文庫"
              }
            },
            {
              "text": "河原にずらりと並んでいる異形の重傷者の眼が、傷ついていない人間を不思議そうに振りむいて眺めた。",
              "citation": {
                "source": "鎮魂歌",
                "author": "原民喜",
                "note": "青空文庫"
              }
            },
            {
              "text": "重傷者の来て呑む泉。",
              "citation": {
                "source": "鎮魂歌",
                "author": "原民喜",
                "note": "青空文庫"
              }
            },
            {
              "text": "それから、あの日あの河原にずらりと並んでいた物凄い重傷者の裸体群像にしたところで、まるで小さな洞窟のなかにぎっしり詰め込められている不思議と可憐な粘土細工か何かのように夢のなかでは現れてくる。",
              "citation": {
                "source": "鎮魂歌",
                "author": "原民喜",
                "note": "青空文庫"
              }
            }
          ]
        }
      }
    ],
    "relations": {
      "homophones": [],
      "synonyms": [],
      "antonyms": [],
      "related": []
    },
    "meta": {
      "version": "1.0.0",
      "source": "JMdict, Aozora-Crawler, Illusions-Core",
      "updated_at": "2026-03-22T12:50:57Z"
    }
  },
  {
    "uuid": "c0e10205-28e9-595f-84de-df1f98209977",
    "entry": "重症者",
    "reading": {
      "primary": "じゅうしょうしゃ",
      "alternatives": [],
      "is_heteronym": false
    },
    "grammar": {
      "pos": [
        "名詞"
      ],
      "ctype": null,
      "inflections": null
    },
    "definitions": [
      {
        "index": 1,
        "gloss": "seriously ill patient",
        "register": "standard",
        "nuance": null,
        "scenarios": [],
        "sensory_tags": {
          "colors": [],
          "temperature": null,
          "sounds": [],
          "emotions": []
        },
        "collocations": [],
        "examples": {
          "standard": [],
          "literary": [
            {
              "text": "すべていつもの通りにやってくれるんだぞ」「畏りました」　閣下と呼ばれたその重症者の声音は、たしかに聞き覚えのあるものであった。",
              "citation": {
                "source": "人造人間殺害事件",
                "author": "海野十三",
                "note": "青空文庫"
              }
            },
            {
              "text": "死にかかった重症者がその上に横たわって、他は繃帯でありガーゼであり、義足であり松葉杖であった。",
              "citation": {
                "source": "いのちの初夜",
                "author": "北條民雄",
                "note": "青空文庫"
              }
            },
            {
              "text": "けれどかういふことを言へば、重症者たちは一笑にふしてしまふであらう。",
              "citation": {
                "source": "柊の垣のうちから",
                "author": "北條民雄",
                "note": "青空文庫"
              }
            },
            {
              "text": "奈落の底から聴えて来るのかと怪しまれる重症者の嗄声と、鬱積した精力を爆発させるやうな青年患者の叫び声とが交錯した。",
              "citation": {
                "source": "盂蘭盆",
                "author": "北條民雄",
                "note": "青空文庫"
              }
            },
            {
              "text": "それでもさすがに重症者は横からじつと眺めるだけで我慢してゐた。",
              "citation": {
                "source": "盂蘭盆",
                "author": "北條民雄",
                "note": "青空文庫"
              }
            },
            {
              "text": "僕のいた東大神経科は、重症者を置かない。",
              "citation": {
                "source": "精神病覚え書",
                "author": "坂口安吾",
                "note": "青空文庫"
              }
            },
            {
              "text": "僕のいた病棟は重症者がいないのだから、病状について僕は良く知らないし、特に僕は一人だけの別室にいたから、廊下や便所ですれ違う以外に、他の患者とは特別の接触がなかった。",
              "citation": {
                "source": "精神病覚え書",
                "author": "坂口安吾",
                "note": "青空文庫"
              }
            },
            {
              "text": "僕の病院では重症者の病室がないので、兇暴患者が現われると、ナルコポンで眠らせて松沢へ送るそうです。",
              "citation": {
                "source": "日月様",
                "author": "坂口安吾",
                "note": "青空文庫"
              }
            },
            {
              "text": "そうして十時間ののちには、死人と重症者がトンネルの中から運ばれて、ちょうどその影のあらわれた場所へ来たのです」　わたしは不気味な戦慄を感じたが、つとめてそれを押しこらえた。",
              "citation": {
                "source": "世界怪談名作集",
                "author": "信号手",
                "note": "青空文庫"
              }
            },
            {
              "text": "今日はいよいよ体力の尽き果てた感じで、どうかすると、私たちがいちばん重症者じゃないかしら、患者はこんなにしゃべるのに、私たちは返事ひとつするのさえ考えるほどだ。",
              "citation": {
                "source": "長崎の鐘",
                "author": "永井隆",
                "note": "青空文庫"
              }
            },
            {
              "text": "少なくとも重症者ではなく、コレラが流行したときに具合の悪いものが２人いたがひどくはなかった。",
              "citation": {
                "source": "コレラの伝染様式について",
                "author": "ON THE MODE OF COMMUNICATION OF CHOLERA (1854)",
                "note": "青空文庫"
              }
            },
            {
              "text": "終戰後二年ほどして、彼は『重症者の兇器』といふ短い文章を書いてゐる。",
              "citation": {
                "source": "三島由紀夫",
                "author": "ナルシシスムの運命",
                "note": "青空文庫"
              }
            },
            {
              "text": "」（『重症者の兇器』後段）ボオドレールの『旅への誘ひ』のルフランが、この青年強盜の耳にも、なつかしく響きつづけてゐたことが察せられる。",
              "citation": {
                "source": "三島由紀夫",
                "author": "ナルシシスムの運命",
                "note": "青空文庫"
              }
            },
            {
              "text": "北の病棟の一番は重症者の部屋で、去定が病人の枕元に坐っており、登がはいってゆくと、見向きもせずに手で招き、そして、診察してみろと云った。",
              "citation": {
                "source": "赤ひげ診療譚",
                "author": "駈込み訴え",
                "note": "青空文庫"
              }
            }
          ]
        }
      }
    ],
    "relations": {
      "homophones": [],
      "synonyms": [],
      "antonyms": [],
      "related": []
    },
    "meta": {
      "version": "1.0.0",
      "source": "JMdict, Aozora-Crawler, Illusions-Core",
      "updated_at": "2026-03-22T12:50:57Z"
    }
  }
]