[
  {
    "uuid": "7ee35ae6-75af-5653-b3b5-8996ce16091b",
    "entry": "ビーコンステーション",
    "reading": {
      "primary": "ビーコンステーション",
      "alternatives": [
        "ビーコン・ステーション"
      ],
      "is_heteronym": false
    },
    "grammar": {
      "pos": [
        "名詞"
      ],
      "ctype": null,
      "inflections": null
    },
    "definitions": [
      {
        "index": 1,
        "gloss": "beaconing station",
        "register": "standard",
        "nuance": null,
        "scenarios": [],
        "sensory_tags": {
          "colors": [],
          "temperature": null,
          "sounds": [],
          "emotions": []
        },
        "collocations": [],
        "examples": {
          "standard": [],
          "literary": []
        }
      }
    ],
    "relations": {
      "homophones": [],
      "synonyms": [],
      "antonyms": [],
      "related": []
    },
    "meta": {
      "version": "1.0.0",
      "source": "JMdict, Aozora-Crawler, Illusions-Core",
      "updated_at": "2026-03-22T12:50:57Z"
    }
  }
]