[
  {
    "uuid": "5eb91836-7c0e-5c42-9186-584489aa0f76",
    "entry": "図書係",
    "reading": {
      "primary": "としょがかり",
      "alternatives": [],
      "is_heteronym": false
    },
    "grammar": {
      "pos": [
        "名詞"
      ],
      "ctype": null,
      "inflections": null
    },
    "definitions": [
      {
        "index": 1,
        "gloss": "librarian",
        "register": "standard",
        "nuance": null,
        "scenarios": [],
        "sensory_tags": {
          "colors": [],
          "temperature": null,
          "sounds": [],
          "emotions": []
        },
        "collocations": [],
        "examples": {
          "standard": [],
          "literary": [
            {
              "text": "あとで知ったことだが、佐和山女史は図書係主任を兼任していてこの室に席があるとのこと、その前の小さな机の一つには一脚の椅子が空のまま並んでいた。",
              "citation": {
                "source": "階段",
                "author": "海野十三",
                "note": "青空文庫"
              }
            },
            {
              "text": "「図書係の京町ミチ子嬢。",
              "citation": {
                "source": "階段",
                "author": "海野十三",
                "note": "青空文庫"
              }
            },
            {
              "text": "而して其の原因はずつと以前に溯ることで、当時コッペは、コメデー・フランセーズ座の図書係をしてゐたので、毎日午後から悠々と出勤したものであつた。",
              "citation": {
                "source": "フランソア・コッペ訪問記",
                "author": "堀口九萬一",
                "note": "青空文庫"
              }
            },
            {
              "text": "コッペは親切で人好きはよい男だが、図書係りの職務には余り熱心といふ程ではなかつた。",
              "citation": {
                "source": "フランソア・コッペ訪問記",
                "author": "堀口九萬一",
                "note": "青空文庫"
              }
            },
            {
              "text": "処が或日コクランがやつて来て図書館の書類の整理が不行届だなどぶつぶつ小言を言つた挙句に「図書係りは月給を貰つてゐないのか」と毒づいた。",
              "citation": {
                "source": "フランソア・コッペ訪問記",
                "author": "堀口九萬一",
                "note": "青空文庫"
              }
            },
            {
              "text": "中に入つて色々となだめたり、すかしたりした人もあつたが、コッペは自分の威厳に関する問題だからといつて、頑として聴き入れず、たうとうコメデー・フランセーズの図書係を退職してしまつた。",
              "citation": {
                "source": "フランソア・コッペ訪問記",
                "author": "堀口九萬一",
                "note": "青空文庫"
              }
            },
            {
              "text": "そのあげくが和作はやはり此の寄宿学校で独逸語の授業のほかに、少年寮の図書係といふ呑気な役目を世話して貰ふ事になつたのである。",
              "citation": {
                "source": "朧夜",
                "author": "犬養健",
                "note": "青空文庫"
              }
            },
            {
              "text": "この図書係といふ役は、手当が余計に貰へる関係から野田が独りぎめに添へて置いたものだつた。",
              "citation": {
                "source": "朧夜",
                "author": "犬養健",
                "note": "青空文庫"
              }
            },
            {
              "text": "図書係の人がもととかわっていました。",
              "citation": {
                "source": "獄中への手紙",
                "author": "一九三九年（昭和十四年）",
                "note": "青空文庫"
              }
            },
            {
              "text": "「さあ、読め、読め、庭をうろつき回っているより、図書係りにでもなったほうがましだろう。",
              "citation": {
                "source": "カラマゾフの兄弟",
                "author": "上",
                "note": "青空文庫"
              }
            },
            {
              "text": "三　三日ほど前から、御番城の蔵方では、武器係り、道具係り、図書係りなど総勢で、例年のように、御蔵の風入れにかかって、毎日、虫｜干に忙殺されていた。",
              "citation": {
                "source": "夏虫行燈",
                "author": "吉川英治",
                "note": "青空文庫"
              }
            },
            {
              "text": "御蔵奉行の岩瀬志摩が、台帳にあわせて、順々に、検分してくるうち、図書係り海野甚三郎が持場の品が一点、不足している事実を発見した。",
              "citation": {
                "source": "夏虫行燈",
                "author": "吉川英治",
                "note": "青空文庫"
              }
            },
            {
              "text": "』『いう迄もなく、図書係りの甚三郎を疑うしかあるまい』『だが、彼んな物を、盗んでどうするか』『金になるさ』『なるかな？",
              "citation": {
                "source": "夏虫行燈",
                "author": "吉川英治",
                "note": "青空文庫"
              }
            }
          ]
        }
      }
    ],
    "relations": {
      "homophones": [],
      "synonyms": [],
      "antonyms": [],
      "related": []
    },
    "meta": {
      "version": "1.0.0",
      "source": "JMdict, Aozora-Crawler, Illusions-Core",
      "updated_at": "2026-03-22T12:50:57Z"
    }
  }
]